markitdown_yaml/__about__.py
markitdown_yaml/__init__.py
markitdown_yaml/_plugin.py
markitdown_yaml/py.typed
markitdown_yaml-0.1.0.dist-info/METADATA
markitdown_yaml-0.1.0.dist-info/WHEEL
markitdown_yaml-0.1.0.dist-info/entry_points.txt
markitdown_yaml-0.1.0.dist-info/licenses/LICENSE
markitdown_yaml-0.1.0.dist-info/RECORD
