Metadata-Version: 2.4
Name: markitdown-yaml
Version: 0.1.0
Summary: A markitdown plugin to convert YAML files
Project-URL: Homepage, https://github.com/YasirAlibrahem/markitdown-yaml
Project-URL: Repository, https://github.com/YasirAlibrahem/markitdown-yaml
Author-email: Yasir Alibrahem <alibrahem.yasir@gmail.com>
License-Expression: MIT
License-File: LICENSE
Keywords: markdown,markitdown,plugin,yaml
Classifier: Development Status :: 3 - Alpha
Classifier: Environment :: Plugins
Classifier: Intended Audience :: Developers
Classifier: License :: OSI Approved :: MIT License
Classifier: Programming Language :: Python
Classifier: Programming Language :: Python :: 3
Classifier: Programming Language :: Python :: 3.10
Classifier: Topic :: Text Processing :: Markup
Classifier: Topic :: Utilities
Requires-Python: >=3.10
Requires-Dist: markitdown>=0.1.0
Requires-Dist: ruamel-yaml>=0.17.0
Provides-Extra: dev
Requires-Dist: mypy>=1.0.0; extra == 'dev'
Requires-Dist: pytest-cov>=4.0.0; extra == 'dev'
Requires-Dist: pytest>=7.0.0; extra == 'dev'
Requires-Dist: ruff>=0.8.0; extra == 'dev'
Provides-Extra: test
Requires-Dist: pytest-cov>=4.0.0; extra == 'test'
Requires-Dist: pytest>=7.0.0; extra == 'test'
